pyerlamsa/__init__.py
pyerlamsa-0.1.dist-info/LICENSE
pyerlamsa-0.1.dist-info/METADATA
pyerlamsa-0.1.dist-info/WHEEL
pyerlamsa-0.1.dist-info/top_level.txt
pyerlamsa-0.1.dist-info/RECORD
