Metadata-Version: 2.1
Name: pyerlamsa
Version: 0.1
Summary: Python client for erlamsa fuzzer
Home-page: http://github.com/Darkkey/pyerlamsa
Author: Alexander Bolshev
Author-email: UNKNOWN
License: MIT
Platform: UNKNOWN
Requires-Dist: requests
